{
  "size": 10,
  "current": 1,
  "count": 5,
  "order": "visits",
  "total": 20,
  "list": [
    {
      "visits": 10000,
      "create_time": "2020-10-12 13:04:22",
      "type": "博客",
      "title": "关于xxxx",
      "summary": "的范德萨范德萨范德萨范德萨的萨芬阿斯顿幅度萨芬大师傅的萨芬的萨芬撒反对啊范德萨发大水",
      "comments": 100,
      "id": "23213dfsd45"
    },
    {
      "visits": 10000,
      "create_time": "2020-10-12 13:04:22",
      "type": "笔记",
      "title": "关于xxxx",
      "summary": "的范德萨范德萨范德萨范德萨的萨芬阿斯顿幅度萨芬大师傅的萨芬的萨芬撒反对啊范德萨发大水",
      "comments": 100,
      "id": "23213dfsd45"
    },
    {
      "visits": 10000,
      "create_time": "2020-10-12 13:04:22",
      "type": "博客",
      "title": "关于xxxx",
      "summary": "的范德萨范德萨范德萨范德萨的萨芬阿斯顿幅度萨芬大师傅的萨芬的萨芬撒反对啊范德萨发大水",
      "comments": 100,
      "id": "23213dfsd45"
    },
    {
      "visits": 10000,
      "create_time": "2020-10-12 13:04:22",
      "type": "博客",
      "title": "关于xxxx",
      "summary": "的范德萨范德萨范德萨范德萨的萨芬阿斯顿幅度萨芬大师傅的萨芬的萨芬撒反对啊范德萨发大水",
      "comments": 100,
      "id": "23213dfsd45"
    },
    {
      "visits": 10000,
      "create_time": "2020-10-12 13:04:22",
      "type": "博客",
      "title": "关于xxxx",
      "summary": "的范德萨范德萨范德萨范德萨的萨芬阿斯顿幅度萨芬大师傅的萨芬的萨芬撒反对啊范德萨发大水",
      "comments": 100,
      "id": "23213dfsd45"
    },
    {
      "visits": 10000,
      "create_time": "2020-10-12 13:04:22",
      "type": "博客",
      "title": "关于xxxx",
      "summary": "的范德萨范德萨范德萨范德萨的萨芬阿斯顿幅度萨芬大师傅的萨芬的萨芬撒反对啊范德萨发大水",
      "comments": 100,
      "id": "23213dfsd45"
    },
    {
      "visits": 10000,
      "create_time": "2020-10-12 13:04:22",
      "type": "博客",
      "title": "关于xxxx",
      "summary": "的范德萨范德萨范德萨范德萨的萨芬阿斯顿幅度萨芬大师傅的萨芬的萨芬撒反对啊范德萨发大水",
      "comments": 100,
      "id": "23213dfsd45"
    },
    {
      "visits": 10000,
      "create_time": "2020-10-12 13:04:22",
      "type": "博客",
      "title": "关于xxxx",
      "summary": "的范德萨范德萨范德萨范德萨的萨芬阿斯顿幅度萨芬大师傅的萨芬的萨芬撒反对啊范德萨发大水",
      "comments": 100,
      "id": "23213dfsd45"
    },
    {
      "visits": 10000,
      "create_time": "2020-10-12 13:04:22",
      "type": "博客",
      "title": "关于xxxx",
      "summary": "的范德萨范德萨范德萨范德萨的萨芬阿斯顿幅度萨芬大师傅的萨芬的萨芬撒反对啊范德萨发大水",
      "comments": 100,
      "id": "23213dfsd45"
    },
    {
      "visits": 10000,
      "create_time": "2020-10-12 13:04:22",
      "type": "博客",
      "title": "关于xxxx",
      "summary": "的范德萨范德萨范德萨范德萨的萨芬阿斯顿幅度萨芬大师傅的萨芬的萨芬撒反对啊范德萨发大水",
      "comments": 100,
      "id": "23213dfsd45"
    }
  ]
}